data_mountains/__init__.py
data_mountains/_modidx.py
data_mountains/core.py
data_mountains/mountainise.py
data_mountains-0.0.5.dist-info/LICENSE
data_mountains-0.0.5.dist-info/METADATA
data_mountains-0.0.5.dist-info/WHEEL
data_mountains-0.0.5.dist-info/entry_points.txt
data_mountains-0.0.5.dist-info/top_level.txt
data_mountains-0.0.5.dist-info/RECORD
