Metadata-Version: 2.1
Name: data-mountains
Version: 0.0.5
Summary: turn a geodataframe of points into mountains, scaled by a data attribute associated with each point
Home-page: https://github.com/joel-lbth/data-mountains
Author: joel
Author-email: joeldn@pm.me
License: agplv3
Keywords: nbdev jupyter notebook python
Classifier: Development Status :: 4 - Beta
Classifier: Intended Audience :: Developers
Classifier: Natural Language :: English
Classifier: Programming Language :: Python :: 3.7
Classifier: Programming Language :: Python :: 3.8
Classifier: Programming Language :: Python :: 3.9
Classifier: Programming Language :: Python :: 3.10
Requires-Python: >=3.7
License-File: LICENSE
Provides-Extra: dev
